LICENSE
README.md
setup.cfg
setup.py
sescore2/README.md
sescore2/SEScore2.py
sescore2/__init__.py
sescore2/downloader.py
sescore2/mistake_pair.py
sescore2/run_regression_model.sh
sescore2/run_severe_final_data.sh
sescore2/run_severity_measure.sh
sescore2/run_syn_data_gen.sh
sescore2.egg-info/PKG-INFO
sescore2.egg-info/SOURCES.txt
sescore2.egg-info/dependency_links.txt
sescore2.egg-info/requires.txt
sescore2.egg-info/top_level.txt
sescore2/inference/__init__.py
sescore2/inference/benchmark_baseline_emb.py
sescore2/inference/d2t_results.py
sescore2/inference/d2t_setup.sh
sescore2/inference/data_to_text.py
sescore2/inference/eval_d2t.py
sescore2/inference/frank.py
sescore2/inference/gen_tsv_de_en.py
sescore2/inference/inference.py
sescore2/inference/inference_regression.py
sescore2/inference/log_scores_wandb.py
sescore2/inference/mis_align_zh_en_med.py
sescore2/inference/prepare_paws.py
sescore2/inference/process_en_de.py
sescore2/inference/process_en_ja_benchmark.py
sescore2/inference/process_ja_benchmark.py
sescore2/inference/process_webnlg.py
sescore2/inference/process_xlsx.py
sescore2/inference/setup_baselines.sh
sescore2/inference/test_all_metrics.py
sescore2/inference/test_sescore.py
sescore2/inference/william_seg_test.py
sescore2/inference/wmt_as_metric.py
sescore2/preprocess/file_divide.py
sescore2/preprocess/merge.py
sescore2/preprocess/merge_dist_id.py
sescore2/preprocess/news_preprocess.py
sescore2/preprocess/pre_split_ende.py
sescore2/preprocess/preprocess_pretrain_data.py
sescore2/preprocess/txt_gen.py
sescore2/syn_data/biimt.py
sescore2/syn_data/biimt_gen_data.py
sescore2/syn_data/construct_news_data.py
sescore2/syn_data/construct_pos_easy_neg.py
sescore2/syn_data/data.py
sescore2/syn_data/del_de_severe_measure.py
sescore2/syn_data/del_severe_measure.py
sescore2/syn_data/download_mc4.py
sescore2/syn_data/edit_ops_ret.py
sescore2/syn_data/epoch_bleu_eval.py
sescore2/syn_data/extract_neg.py
sescore2/syn_data/faiss_run.py
sescore2/syn_data/final_data_construct.py
sescore2/syn_data/final_merge.py
sescore2/syn_data/fix_severe_score.py
sescore2/syn_data/gen_eval_data.py
sescore2/syn_data/knn_search.py
