Metadata-Version: 2.1
Name: sescore2
Version: 1.0.5
Summary: SESCORE2: Learning Text Generation Evaluation via Synthesizing Realistic Mistakes
Home-page: https://github.com/xu1998hz/SEScore2_archive
Author: Wenda Xu, Xian Qian, Mingxuan Wang, Lei Li, William Yang Wang
Author-email: wendaxu@ucsb.edu
Maintainer: Wenda Xu, Zihan Ma
Maintainer-email: zihan_ma@ucsb.edu
Requires-Python: >=3.8.0,<4.0.0
License-File: LICENSE
Requires-Dist: transformers
Requires-Dist: accelerate==0.20.3
Requires-Dist: sentencepiece
Requires-Dist: protobuf==3.20.*
Requires-Dist: python-snappy
Requires-Dist: pandas
Requires-Dist: nvitop
Requires-Dist: click
Requires-Dist: datasets
Requires-Dist: wandb
Requires-Dist: scipy
Requires-Dist: absl-py
Requires-Dist: torch
Requires-Dist: torchvision
Requires-Dist: torchaudio
